replacements.py
replacements-1.0.dist-info/LICENSE
replacements-1.0.dist-info/METADATA
replacements-1.0.dist-info/WHEEL
replacements-1.0.dist-info/top_level.txt
replacements-1.0.dist-info/RECORD
