Metadata-Version: 2.1
Name: replacements
Version: 1.0
Summary: Replace strings with other strings
Home-page: http://github.com/drorspei/replacements
Author: Dror Speiser
License: MIT
Platform: UNKNOWN
License-File: LICENSE
